django_admin_ai/__init__.py
django_admin_ai/admin.py
django_admin_ai/apps.py
django_admin_ai/models.py
django_admin_ai/tests.py
django_admin_ai/urls.py
django_admin_ai/views.py
django_admin_ai/migrations/__init__.py
django_admin_ai/templates/admin/change_form.html
django_admin_ai-0.1.5.dist-info/LICENSE
django_admin_ai-0.1.5.dist-info/METADATA
django_admin_ai-0.1.5.dist-info/WHEEL
django_admin_ai-0.1.5.dist-info/top_level.txt
django_admin_ai-0.1.5.dist-info/RECORD
