Metadata-Version: 2.2
Name: django-admin-ai
Version: 0.1.5
Summary: An AI-powered assistant for Django Admin, allowing data import using OpenAI.
Home-page: https://github.com/aritzjl/django-admin-ai
Author: Aritz Jaber Lopes
Author-email: aritzzjl@gmail.com
Classifier: Development Status :: 4 - Beta
Classifier: Framework :: Django
Classifier: Intended Audience :: Developers
Classifier: License :: OSI Approved :: MIT License
Classifier: Programming Language :: Python :: 3
Classifier: Programming Language :: Python :: 3.7
Classifier: Programming Language :: Python :: 3.8
Classifier: Programming Language :: Python :: 3.9
Requires-Python: >=3.7
License-File: LICENSE
Requires-Dist: Django>=3.2
Requires-Dist: openai>=1.61.0
Requires-Dist: annotated-types==0.7.0
Requires-Dist: anyio==4.8.0
Requires-Dist: asgiref==3.8.1
Requires-Dist: build==1.2.2.post1
Requires-Dist: certifi==2025.1.31
Requires-Dist: colorama==0.4.6
Requires-Dist: distro==1.9.0
Requires-Dist: h11==0.14.0
Requires-Dist: httpcore==1.0.7
Requires-Dist: httpx==0.28.1
Requires-Dist: idna==3.10
Requires-Dist: jiter==0.8.2
Requires-Dist: packaging==24.2
Requires-Dist: pydantic==2.10.6
Requires-Dist: pydantic_core==2.27.2
Requires-Dist: pyproject_hooks==1.2.0
Requires-Dist: setuptools==75.8.0
Requires-Dist: sniffio==1.3.1
Requires-Dist: sqlparse==0.5.3
Requires-Dist: tqdm==4.67.1
Requires-Dist: typing_extensions==4.12.2
Requires-Dist: tzdata==2025.1
Requires-Dist: PyPDF2>=2.10.1
Requires-Dist: python-doctr==0.11.0
Requires-Dist: Pillow>=8.0.0
Requires-Dist: torch==2.6.0
Requires-Dist: torchvision==0.21.0
Dynamic: author
Dynamic: author-email
Dynamic: classifier
Dynamic: description
Dynamic: description-content-type
Dynamic: home-page
Dynamic: requires-dist
Dynamic: requires-python
Dynamic: summary
